LICENSE
crustinterface/__init__.py
crustinterface/base.py
crustinterface/constants.py
crustinterface/decorators.py
crustinterface/mainnet.py
crustinterface/parachain.py
crustinterface/shadow.py
crust_interface_patara-0.2.0.dist-info/LICENSE
crust_interface_patara-0.2.0.dist-info/WHEEL
crust_interface_patara-0.2.0.dist-info/METADATA
crust_interface_patara-0.2.0.dist-info/RECORD
