Metadata-Version: 2.1
Name: crust-interface-patara
Version: 0.2.0
Summary: A simple tool to interact with Crust Shadow, Crust Polkadot Parachain and Crust Mainnet. Under development
Home-page: https://github.com/PaTara43/crust-interface-patara
License: Apache-2.0
Keywords: python,ipfs,web3,substrate,crust,pypi-package,polkadot
Author: PaTara43
Author-email: p040399@outlook.com
Requires-Python: >=3.8,<4.0
Classifier: License :: OSI Approved :: Apache Software License
Classifier: Operating System :: Unix
Classifier: Programming Language :: Python :: 3
Classifier: Programming Language :: Python :: 3.8
Classifier: Programming Language :: Python :: 3.9
Classifier: Programming Language :: Python :: 3.10
Classifier: Programming Language :: Python :: 3.11
Classifier: Programming Language :: Python :: 3
Classifier: Topic :: Scientific/Engineering :: Human Machine Interfaces
Classifier: Topic :: Software Development :: Documentation
Classifier: Topic :: Software Development :: Libraries :: Python Modules
Requires-Dist: substrate-interface (>=1.4.0,<2.0)
Project-URL: Bug Tracker, https://github.com/Multi-Agent-io/crust-interface-patara/issues
Project-URL: Documentation, https://github.com/PaTara43/crust-interface-patara/blob/main/README.md
Project-URL: Repository, https://github.com/PaTara43/crust-interface-patara
